shaman/__init__.py
shaman/bin/__init__.py
shaman/bin/shamancli.py
shaman/etc/crawler.config
shaman/src/__init__.py
shaman/src/abstract_message.py
shaman/src/consumer.py
shaman/src/analyzers/__init__.py
shaman/src/analyzers/abstract_stage.py
shaman/src/analyzers/analyzer_stages/__init__.py
shaman/src/analyzers/analyzer_stages/charsetdetect_stage.py
shaman/src/analyzers/general_stages/__init__.py
shaman/src/analyzers/general_stages/download_stage.py
shaman/src/analyzers/general_stages/download_stage_proxified.py
shaman/src/analyzers/general_stages/message_printer.py
shaman/src/analyzers/input_stages/__init__.py
shaman/src/analyzers/input_stages/crawler_kafka_input_stage.py
shaman/src/analyzers/input_stages/stdin_reader_stage.py
shaman/src/analyzers/output_stages/__init__.py
shaman/src/analyzers/output_stages/file_output_stage.py
shaman/src/analyzers/output_stages/kafka_output_stage.py
shaman/src/analyzers/output_stages/mongo_bulk_output_stage.py
shaman/src/analyzers/output_stages/mongo_output_stage.py
shaman/src/helpers/__init__.py
shaman/src/helpers/abstract_consumer_exceptions.py
shaman/src/helpers/analyzer_exceptions.py
shaman/src/helpers/configuration_change.py
shaman/src/helpers/configuration_exceptions.py
shaman/src/helpers/daemon_exceptions.py
shaman/src/helpers/graphite.py
shaman/src/helpers/kafka_exceptions.py
shaman/src/helpers/mongo_accessor.py
shaman/src/helpers/mongo_accessor_exceptions.py
shaman/src/helpers/tree_searcher.py
shaman/src/helpers/url_helpers.py
shaman/tests/__init__.py
shaman/tests/helpers/__init__.py
shaman/tests/helpers/test_mongo_accessor_roll_out.py
shaman/tests/helpers/test_tree_searcher.py
shaman/tests/helpers/test_url_helpers.py
shaman/tests/helpers/test_url_helpers3.py
shaman/tests/helpers/train_sets.py
shaman-0.1.0.dev1.dist-info/DESCRIPTION.rst
shaman-0.1.0.dev1.dist-info/METADATA
shaman-0.1.0.dev1.dist-info/RECORD
shaman-0.1.0.dev1.dist-info/WHEEL
shaman-0.1.0.dev1.dist-info/entry_points.txt
shaman-0.1.0.dev1.dist-info/metadata.json
shaman-0.1.0.dev1.dist-info/top_level.txt
