Metadata-Version: 2.0
Name: shaman
Version: 0.1.0.dev1
Summary: Multiprocessing application to download and analyze a content of an html pages.
Home-page: https://github.com/Landish145/shaman
Author: eugtsa,azraev
Author-email: eugtsa@gmail.com,azraev@gmail.com
License: MIT
Keywords: crawlers analyze development
Platform: UNKNOWN
Classifier: Development Status :: 3 - Alpha
Classifier: Intended Audience :: Developers
Classifier: Topic :: Software Development :: Build Tools
Classifier: Natural Language :: English
Classifier: License :: OSI Approved :: MIT License
Classifier: Operating System :: MacOS :: MacOS X
Classifier: Programming Language :: Python :: 2
Classifier: Programming Language :: Python :: 2.6
Classifier: Programming Language :: Python :: 2.7
Classifier: Programming Language :: Python :: 3
Classifier: Programming Language :: Python :: 3.3
Classifier: Programming Language :: Python :: 3.4
Classifier: Programming Language :: Python :: 3.5
Requires-Dist: argparse
Requires-Dist: bson
Requires-Dist: configparser
Requires-Dist: grab
Requires-Dist: kafka-python
Requires-Dist: pyformance
Provides-Extra: dev
Requires-Dist: check-manifest; extra == 'dev'
Provides-Extra: test
Requires-Dist: coverage; extra == 'test'
